util_process_pool/__init__.py
util_process_pool/process_pool.py
util_process_pool-0.1.0.dist-info/licenses/LICENSE
util_process_pool-0.1.0.dist-info/METADATA
util_process_pool-0.1.0.dist-info/WHEEL
util_process_pool-0.1.0.dist-info/top_level.txt
util_process_pool-0.1.0.dist-info/RECORD
