Metadata-Version: 2.4
Name: util-process-pool
Version: 0.1.0
Summary: 简便的多进程调用工具，基于 concurrent.futures.ProcessPoolExecutor 的封装
Author-email: birds <cg626@163.com>
License-Expression: MIT
Requires-Python: >=3.7
License-File: LICENSE
Requires-Dist: click>=8.0.0
Provides-Extra: dev
Requires-Dist: pytest>=6.0; extra == "dev"
Requires-Dist: black>=21.0; extra == "dev"
Requires-Dist: flake8>=3.9; extra == "dev"
Dynamic: license-file
